coral/__init__.py
coral/data.py
coral/main.py
coral/utility.py
ccore_coral-0.1.5.dist-info/METADATA
ccore_coral-0.1.5.dist-info/WHEEL
ccore_coral-0.1.5.dist-info/entry_points.txt
ccore_coral-0.1.5.dist-info/RECORD
