Metadata-Version: 2.4
Name: ccore-coral
Version: 0.1.5
Summary: 
Author: Toan Phung
Author-email: toan.phung@proteo.info
Requires-Python: >=3.10,<3.12
Classifier: Programming Language :: Python :: 3
Classifier: Programming Language :: Python :: 3.10
Classifier: Programming Language :: Python :: 3.11
Requires-Dist: click (>=8.1.7,<9.0.0)
Requires-Dist: numpy (>=2.1.0,<2.2.0)
Requires-Dist: pandas (>=2.2.3,<2.3.0)
Requires-Dist: python-on-whales (>=0.67.0,<0.68.0)
Requires-Dist: rpy2 (==3.5.12)
Requires-Dist: scipy (>=1.15.2,<1.16.0)
Requires-Dist: seaborn (>=0.13.2,<0.14.0)
